nix_manipulator/__init__.py
nix_manipulator/__main__.py
nix_manipulator/cli.py
nix_manipulator/exceptions.py
nix_manipulator/format.py
nix_manipulator/manipulations.py
nix_manipulator/mapping.py
nix_manipulator/parser.py
nix_manipulator/utils.py
nix_manipulator/expressions/__init__.py
nix_manipulator/expressions/assertion.py
nix_manipulator/expressions/binary.py
nix_manipulator/expressions/binding.py
nix_manipulator/expressions/comment.py
nix_manipulator/expressions/ellipses.py
nix_manipulator/expressions/expression.py
nix_manipulator/expressions/identifier.py
nix_manipulator/expressions/indented_string.py
nix_manipulator/expressions/inherit.py
nix_manipulator/expressions/layout.py
nix_manipulator/expressions/let.py
nix_manipulator/expressions/list.py
nix_manipulator/expressions/operator.py
nix_manipulator/expressions/parenthesis.py
nix_manipulator/expressions/path.py
nix_manipulator/expressions/primitive.py
nix_manipulator/expressions/select.py
nix_manipulator/expressions/set.py
nix_manipulator/expressions/source_code.py
nix_manipulator/expressions/unary.py
nix_manipulator/expressions/with_statement.py
nix_manipulator/expressions/function/__init__.py
nix_manipulator/expressions/function/call.py
nix_manipulator/expressions/function/definition.py
nix_manipulator-0.1.3.dist-info/METADATA
nix_manipulator-0.1.3.dist-info/WHEEL
nix_manipulator-0.1.3.dist-info/entry_points.txt
nix_manipulator-0.1.3.dist-info/licenses/COPYING
nix_manipulator-0.1.3.dist-info/licenses/COPYING.LESSER
nix_manipulator-0.1.3.dist-info/licenses/LICENSE
nix_manipulator-0.1.3.dist-info/RECORD
