Metadata-Version: 2.4
Name: nix-manipulator
Version: 0.1.3
Summary: A Python library for parsing, manipulating, and reconstructing Nix source code with high-level abstractions while preserving formatting and comments in RFC-formatted code.
Project-URL: Homepage, https://codeberg.org/hoh/nix-manipulator
Project-URL: Source, https://codeberg.org/hoh/nix-manipulator
Project-URL: Tracker, https://codeberg.org/hoh/nix-manipulator/issues
Author-email: Hugo Herter <git@hugoherter.com>
License-Expression: LGPL-3.0-or-later
License-File: COPYING
License-File: COPYING.LESSER
License-File: LICENSE
Keywords: ast,code-manipulation,nix,parsing
Classifier: Development Status :: 4 - Beta
Classifier: Intended Audience :: Developers
Classifier: License :: OSI Approved :: GNU Lesser General Public License v3 or later (LGPLv3+)
Classifier: Programming Language :: Python :: 3
Classifier: Programming Language :: Python :: 3.11
Classifier: Programming Language :: Python :: 3.12
Classifier: Programming Language :: Python :: 3.13
Classifier: Topic :: Software Development :: Libraries :: Python Modules
Requires-Python: >=3.11
Requires-Dist: pydantic>=2.11.4
Requires-Dist: pygments>=2.19.1
Requires-Dist: tree-sitter-nix>=0.1.0
Requires-Dist: tree-sitter>=0.24.0
